MANIFEST.in
README.rst
setup.py
authentication/__init__.py
authentication/apps.py
authentication/middleware.py
authentication/models.py
authentication/tests.py
authentication/urls.py
authentication/views.py
authentication/migrations/__init__.py
authentication/static/.DS_Store
authentication/static/authentication/.DS_Store
authentication/static/authentication/css/authentication-styles.css
authentication/static/authentication/css/bootstrap.min.css
authentication/static/authentication/js/.DS_Store
authentication/static/authentication/js/angular-animate.min.js
authentication/static/authentication/js/angular-aria.min.js
authentication/static/authentication/js/angular-cookies.js
authentication/static/authentication/js/angular-messages.min.js
authentication/static/authentication/js/angular.min.js
authentication/static/authentication/js/authentication-app.js
authentication/static/authentication/js/bootstrap.min.js
authentication/static/authentication/js/jquery.min.js
authentication/templates/.DS_Store
authentication/templates/authentication/base.html
authentication/templates/authentication/login_register.html
authentication/templates/authentication/scripts.html
integra_authentication.egg-info/PKG-INFO
integra_authentication.egg-info/SOURCES.txt
integra_authentication.egg-info/dependency_links.txt
integra_authentication.egg-info/requires.txt
integra_authentication.egg-info/top_level.txt
integra_authentication.egg-info/zip-safe